ssg/SSGParser.py
ssg/SSGUtil.py
ssg/__init__.py
ssg/ssg.py
ssg_a_rokay-1.0.4.dist-info/LICENSE
ssg_a_rokay-1.0.4.dist-info/METADATA
ssg_a_rokay-1.0.4.dist-info/WHEEL
ssg_a_rokay-1.0.4.dist-info/top_level.txt
ssg_a_rokay-1.0.4.dist-info/RECORD
