Metadata-Version: 2.1
Name: ssg-a-rokay
Version: 1.0.4
Summary: Uses python to generate static html files from a single txt or folder of txt files
Home-page: https://github.com/a-rokay/static-site-generator
Author: Ahmad Rokay
Author-email: arokay@myseneca.ca
License: UNKNOWN
Project-URL: Bug Tracker, https://github.com/a-rokay/static-site-generator/issues
Platform: UNKNOWN
Classifier: Programming Language :: Python :: 3
Classifier: License :: OSI Approved :: MIT License
Classifier: Operating System :: OS Independent
Requires-Python: >=3.6
License-File: LICENSE
